xbox/__init__.py
xbox/xbox.py
xbox_remote-1.0.5.dist-info/LICENSE
xbox_remote-1.0.5.dist-info/METADATA
xbox_remote-1.0.5.dist-info/WHEEL
xbox_remote-1.0.5.dist-info/top_level.txt
xbox_remote-1.0.5.dist-info/RECORD
