Metadata-Version: 2.1
Name: xbox-remote
Version: 1.0.5
Summary: A Python package to connect to xbox and interface with its buttons and joysticks
Home-page: https://github.com/FRC4564/Xbox
Author: Steven Jacobs
License: MIT
Platform: UNKNOWN
Classifier: License :: OSI Approved :: MIT License
Classifier: Programming Language :: Python :: 3
Classifier: Programming Language :: Python :: 3.7
